odoo/addons/ssi_psychology_evaluation_related_attachment/README.rst
odoo/addons/ssi_psychology_evaluation_related_attachment/__init__.py
odoo/addons/ssi_psychology_evaluation_related_attachment/__manifest__.py
odoo/addons/ssi_psychology_evaluation_related_attachment/models/__init__.py
odoo/addons/ssi_psychology_evaluation_related_attachment/models/psychology_evaluation.py
odoo/addons/ssi_psychology_evaluation_related_attachment/models/psychology_evaluation_batch.py
odoo/addons/ssi_psychology_evaluation_related_attachment/static/description/icon.png
odoo/addons/ssi_psychology_evaluation_related_attachment/views/psychology_evaluation_batch_views.xml
odoo/addons/ssi_psychology_evaluation_related_attachment/views/psychology_evaluation_views.xml
odoo14_addon_ssi_psychology_evaluation_related_attachment-14.0.1.2.0.dist-info/METADATA
odoo14_addon_ssi_psychology_evaluation_related_attachment-14.0.1.2.0.dist-info/WHEEL
odoo14_addon_ssi_psychology_evaluation_related_attachment-14.0.1.2.0.dist-info/top_level.txt
odoo14_addon_ssi_psychology_evaluation_related_attachment-14.0.1.2.0.dist-info/RECORD
